{
  "homework": [
    {
      "question_no": 1,
      "lesson_id": 3622535,
      "lesson_title": "Unit 1A: Toys - Lesson 3: How many balls are there?",
      "skill_category": "grammar",
      "question_type": "Một lựa chọn",
      "question_text": "Read and choose the correct word. (Con hãy đọc và chọn từ đúng nhé.) There ... 2 puzzles.",
      "correct_answer": "C. are",
      "difficulty": "easy",
      "reason": "Bài này đã học 111 ngày trước và còn là bài chưa nộp homework, nên nguy cơ quên mẫu câu số nhiều rất cao. Chẩn đoán cho thấy học sinh hay thiếu cấu trúc chủ ngữ–động từ–bổ ngữ và trả lời đứt gãy như “It’s.”, nên cần ôn lại mẫu “There are ...” từ đầu.",
      "question_id": 303807,
      "requires_media": false,
      "speaking_evidence": "It’s.",
      "stem_media_urls": [],
      "comment_media_urls": [],
      "choice_previews": [
        {
          "letter": "A",
          "text": "A. am",
          "image_urls": [],
          "audio_urls": []
        },
        {
          "letter": "B",
          "text": "B. is",
          "image_urls": [],
          "audio_urls": []
        },
        {
          "letter": "C",
          "text": "C. are",
          "image_urls": [],
          "audio_urls": []
        }
      ],
      "comment_plain": "There are 2 puzzles. (Có 2 miếng ghép hình.) => Đáp án: C (tobe \"are\" cộng với danh từ số nhiều)",
      "question_folder": "English Tutoring - Level 2"
    },
    {
      "question_no": 2,
      "lesson_id": 3641688,
      "lesson_title": "Unit 1A: Toys - Lesson 5: There're 5 balls.",
      "skill_category": "grammar",
      "question_type": "Một lựa chọn",
      "question_text": "Read and reorder the sentence (Con hãy đọc và sắp xếp thành câu nhé.) /blocks/'re/There/ten/./",
      "correct_answer": "A. There're ten blocks.",
      "difficulty": "easy",
      "reason": "Bài này đã học 102 ngày trước và cũng chưa nộp homework, nên cần kéo lại trí nhớ về mẫu “There’re ...” thật sớm. Chẩn đoán cho thấy học sinh thường tạo câu ngắn, thiếu thành phần như “Yes, I.” và “The tiger is.”, vì vậy câu sắp xếp lại này giúp củng cố câu hoàn chỉnh.",
      "question_id": 304121,
      "requires_media": false,
      "speaking_evidence": "Yes, I.",
      "stem_media_urls": [],
      "comment_media_urls": [],
      "choice_previews": [
        {
          "letter": "A",
          "text": "A. There're ten blocks.",
          "image_urls": [],
          "audio_urls": []
        },
        {
          "letter": "B",
          "text": "B. There're blocks ten.",
          "image_urls": [],
          "audio_urls": []
        },
        {
          "letter": "C",
          "text": "C. There ten're blocks.",
          "image_urls": [],
          "audio_urls": []
        }
      ],
      "comment_plain": "There're ten blocks: Có 10 khối hình. => Đáp án: A",
      "question_folder": "English Tutoring - Level 2"
    },
    {
      "question_no": 3,
      "lesson_id": 3690827,
      "lesson_title": "Unit 2A: My home - Lesson 5: They're in the living room.",
      "skill_category": "grammar",
      "question_type": "Một lựa chọn",
      "question_text": "Read and reorder the correct sentence (Con hãy đọc và sắp xếp thành câu nhé.) are/ They/ parents/ my/ .",
      "correct_answer": "A. They are my parents.",
      "difficulty": "easy",
      "reason": "Bài này đã học 83 ngày trước — cần ôn lại vì học sinh đã trả lời sai câu này trước đó: điền/chọn \"B. They my are parents.\" thay vì \"A. They are my parents.\". Đây cũng đúng với mẫu lỗi trật tự từ trong chẩn đoán, nơi học sinh từng nói/viết kiểu “They my are parents.”.",
      "question_id": 373426,
      "requires_media": false,
      "speaking_evidence": null,
      "stem_media_urls": [],
      "comment_media_urls": [],
      "choice_previews": [
        {
          "letter": "A",
          "text": "A. They are my parents.",
          "image_urls": [],
          "audio_urls": []
        },
        {
          "letter": "B",
          "text": "B. They my are parents.",
          "image_urls": [],
          "audio_urls": []
        },
        {
          "letter": "C",
          "text": "C. They are parents my.",
          "image_urls": [],
          "audio_urls": []
        }
      ],
      "comment_plain": "They are my parents. Dịch: Họ là bố mẹ của tôi. => Đáp án: A",
      "question_folder": "English Tutoring - Level 2"
    },
    {
      "question_no": 4,
      "lesson_id": 3768630,
      "lesson_title": "Unit 4A: My face - Lesson 4: He has curly hair.",
      "skill_category": "grammar",
      "question_type": "Kéo thả vào chỗ trống trong đoạn văn",
      "question_text": "Fill in blank missing word (Con hãy điền từ vào chỗ trống nhé.) 1. I [{}] big eyes. 2. She [{}] long hair. 3. I have str",
      "correct_answer": "1. I have big eyes. 2. She has long hair. 3. I have straight hair. 4. He has a big nose.",
      "difficulty": "medium",
      "reason": "Bài này đã học 48 ngày trước, đủ lâu để học sinh quên quy tắc have/has nếu không ôn lại. Chẩn đoán cho thấy em hay nói câu thiếu hoặc sai mẫu như “My father is the old.” và “Lion big.”, nên bài điền từ này giúp ổn định lại khung câu mô tả cơ bản.",
      "question_id": 389561,
      "requires_media": false,
      "speaking_evidence": "Lion big.",
      "stem_media_urls": [],
      "comment_media_urls": [],
      "choice_previews": [
        {
          "letter": "1",
          "text": "has",
          "image_urls": [],
          "audio_urls": []
        },
        {
          "letter": "2",
          "text": "hair",
          "image_urls": [],
          "audio_urls": []
        },
        {
          "letter": "3",
          "text": "big",
          "image_urls": [],
          "audio_urls": []
        },
        {
          "letter": "4",
          "text": "have",
          "image_urls": [],
          "audio_urls": []
        }
      ],
      "comment_plain": "has: có (chủ ngữ \"He, She, It\" dùng \"has\") hair: tóc big: to have: có (chủ ngữ \"I, You, We, They\" dùng \"have\") => Đáp án: 1. I have big eyes: Tôi có đôi mắt to. 2. She has long hair: Cô ấy có mái tóc dài. 3. I have straight hair: Tôi có mái tóc thẳng. 4. He has a big nose: Anh ấy có chiếc mũi to.",
      "question_folder": "English Tutoring - Level 2"
    },
    {
      "question_no": 5,
      "lesson_id": 3662593,
      "lesson_title": "Unit 2A: My home - Lesson 2: They're my parents.",
      "skill_category": "vocabulary",
      "question_type": "Một lựa chọn",
      "question_text": "Odd one out. (Con hãy chọn một từ khác loại nhé.)",
      "correct_answer": "C. mother",
      "difficulty": "easy",
      "reason": "Bài này đã học 96 ngày trước — cần ôn lại nhóm từ gia đình vì học sinh đã trả lời sai câu này trước đó: điền/chọn \"A. son\" thay vì \"C. mother\". Đây là bài nền tảng về family members, đúng nhóm kiến thức chẩn đoán cảnh báo là đã học lâu và có rủi ro mất dấu trí nhớ cao.",
      "question_id": 371656,
      "requires_media": false,
      "speaking_evidence": null,
      "stem_media_urls": [],
      "comment_media_urls": [],
      "choice_previews": [
        {
          "letter": "A",
          "text": "A. son",
          "image_urls": [],
          "audio_urls": []
        },
        {
          "letter": "B",
          "text": "B. daughter",
          "image_urls": [],
          "audio_urls": []
        },
        {
          "letter": "C",
          "text": "C. mother",
          "image_urls": [],
          "audio_urls": []
        }
      ],
      "comment_plain": "son: con trai daughter: con gái mother: mẹ => Đáp án: C",
      "question_folder": "English Tutoring - Level 2"
    },
    {
      "question_no": 6,
      "lesson_id": 3768634,
      "lesson_title": "Unit 1B: Animals - Lesson 2: Those are lions and zebras.",
      "skill_category": "grammar",
      "question_type": "Một lựa chọn",
      "question_text": "Choose the correct answer. (Con hãy chọn phương án đúng nhé.) What are these? ___ are lions.",
      "correct_answer": "C. These",
      "difficulty": "easy",
      "reason": "Bài này đã học 34 ngày trước và học sinh đã trả lời sai câu này trước đó: điền/chọn \"B. Those\" thay vì \"C. These\". Chẩn đoán nêu rõ lỗi nền tảng this/that/these/those đang lặp lại nhiều lần, nên cần chặn sớm để tránh nói sai trong hội thoại.",
      "question_id": 308500,
      "requires_media": false,
      "speaking_evidence": null,
      "stem_media_urls": [],
      "comment_media_urls": [],
      "choice_previews": [
        {
          "letter": "A",
          "text": "A. This",
          "image_urls": [],
          "audio_urls": []
        },
        {
          "letter": "B",
          "text": "B. Those",
          "image_urls": [],
          "audio_urls": []
        },
        {
          "letter": "C",
          "text": "C. These",
          "image_urls": [],
          "audio_urls": []
        }
      ],
      "comment_plain": "What are these? These are lions. Dịch: Đây là gì? Đây là những con sư tử. => Đáp án: C (câu hỏi dùng \"these\" --> câu trả lời phải dùng \"These\")",
      "question_folder": "English Tutoring - Level 2"
    },
    {
      "question_no": 7,
      "lesson_id": 3768631,
      "lesson_title": "Unit 4A: My face - Lesson 5: She has short hair.",
      "skill_category": "vocabulary",
      "question_type": "Một lựa chọn",
      "question_text": "Read and choose correct answer (Con hãy đọc và chọn phương án đúng nhé.) I have a ...",
      "correct_answer": "C. big nose",
      "difficulty": "easy",
      "reason": "Bài này đã học 46 ngày trước và học sinh đã trả lời sai câu này trước đó: điền/chọn \"A. big eyes\" thay vì \"C. big nose\". Chẩn đoán cũng cho thấy em hay tạo câu mô tả chưa hoàn chỉnh như “The tiger is.”, nên cần củng cố cụm danh từ đúng trước khi mở rộng thành câu.",
      "question_id": 307422,
      "requires_media": false,
      "speaking_evidence": "The tiger is.",
      "stem_media_urls": [],
      "comment_media_urls": [],
      "choice_previews": [
        {
          "letter": "A",
          "text": "A. big eyes",
          "image_urls": [],
          "audio_urls": []
        },
        {
          "letter": "B",
          "text": "B. small ears",
          "image_urls": [],
          "audio_urls": []
        },
        {
          "letter": "C",
          "text": "C. big nose",
          "image_urls": [],
          "audio_urls": []
        }
      ],
      "comment_plain": "I have a big nose. Dịch: Tôi có một cái mũi to. => Đáp án: C (\"a\" cộng với danh từ số ít)",
      "question_folder": "English Tutoring - Level 2"
    },
    {
      "question_no": 8,
      "lesson_id": 3785565,
      "lesson_title": "Unit 2B: Food - Lesson 1: What food do you like?",
      "skill_category": "speaking",
      "question_type": "free_speaking",
      "question_text": "Answer in 1 full sentence: What food do you like?",
      "correct_answer": null,
      "difficulty": "medium",
      "reason": "Bài này đã học 20 ngày trước nhưng là chủ điểm nói đang yếu rõ theo chẩn đoán; học sinh thường trả lời lệch chủ đề ở câu hỏi đời thường. Điểm free_speaking thuộc nhóm cảnh báo thấp và em từng trả lời không liên quan như “I have a dog.” cho câu hỏi mở, nên cần luyện câu khung “I like ...”.",
      "question_id": null,
      "requires_media": false,
      "speaking_evidence": "I have a dog."
    },
    {
      "question_no": 9,
      "lesson_id": 3814880,
      "lesson_title": "Unit 2B:  Food - Lesson 4: Pizza is yummy.",
      "skill_category": "speaking",
      "question_type": "free_speaking",
      "question_text": "Answer with a full sentence: Do you like fish?",
      "correct_answer": null,
      "difficulty": "medium",
      "reason": "Bài này đã học 11 ngày trước, còn khá mới nên phù hợp để luyện phản xạ nói có khung thay vì hỏi mở hoàn toàn. Chẩn đoán cho thấy học sinh hay trộn mẫu yes/no như “Yes, I do. No, I don’t.”, vì vậy câu này giúp em chọn đúng một đáp án và nói trọn câu.",
      "question_id": null,
      "requires_media": false,
      "speaking_evidence": "Yes, I do. No, I don’t."
    },
    {
      "question_no": 10,
      "lesson_id": 3690826,
      "lesson_title": "Unit 2A: My home - Lesson 4: They're in the garden.",
      "skill_category": "vocabulary",
      "question_type": "Một lựa chọn",
      "question_text": "Listen and choose the correct answer. (Con hãy nghe và chọn phương án đúng nhé.)",
      "correct_answer": "A. Where are they? They're in the bathroom.",
      "difficulty": "medium",
      "reason": "Bài này đã học 90 ngày trước và học sinh đã trả lời sai câu này trước đó: điền/chọn \"B. Where are they? They're in the bedroom.\" thay vì \"A. Where are they? They're in the bathroom.\". Đây là một bài spaced review quan trọng vì chẩn đoán cho thấy em dễ nhầm vị trí trong nhà và cần ôn lại sau thời gian dài.",
      "question_id": 373213,
      "requires_media": false,
      "speaking_evidence": null,
      "stem_media_urls": [],
      "comment_media_urls": [],
      "choice_previews": [
        {
          "letter": "A",
          "text": "A. Where are they? They're in the bathroom.",
          "image_urls": [],
          "audio_urls": []
        },
        {
          "letter": "B",
          "text": "B. Where are they? They're in the bedroom.",
          "image_urls": [],
          "audio_urls": []
        },
        {
          "letter": "C",
          "text": "C. Where are they? They're in the living room.",
          "image_urls": [],
          "audio_urls": []
        }
      ],
      "comment_plain": "Audio: Where are they? They're in the bathroom. Dịch: Họ ở đâu? Họ đang ở trong nhà tắm. => Đáp án: A",
      "question_folder": "English Tutoring - Level 2"
    },
    {
      "question_no": 11,
      "lesson_id": 3690827,
      "lesson_title": "Unit 2A: My home - Lesson 5: They're in the living room.",
      "skill_category": "speaking",
      "question_type": "free_speaking",
      "question_text": "Answer in 1 full sentence: Where's he?",
      "correct_answer": null,
      "difficulty": "medium",
      "reason": "Bài này đã học 83 ngày trước và đúng điểm yếu về phân biệt người–địa điểm trong chẩn đoán. Học sinh đã từng nhầm loại thông tin ở bài cùng lesson khi chọn “He&#39;s my father.” thay vì câu vị trí, nên cần luyện nói mẫu “He’s in the garden/living room.” để tránh trả lời lệch dạng câu hỏi.",
      "question_id": null,
      "requires_media": false,
      "speaking_evidence": null
    },
    {
      "question_no": 12,
      "lesson_id": 3768634,
      "lesson_title": "Unit 1B: Animals - Lesson 2: Those are lions and zebras.",
      "skill_category": "speaking",
      "question_type": "free_speaking",
      "question_text": "Look and answer in 1 sentence: What are these?",
      "correct_answer": null,
      "difficulty": "medium",
      "reason": "Bài này đã học 34 ngày trước và là lỗi nền tảng this/these mà chẩn đoán nhấn mạnh cần deep practice. Học sinh đã từng chọn sai “B. Those” thay vì “C. These” ở cùng lesson, nên cần chuyển từ nhận diện sang nói câu đầy đủ “These are ...”.",
      "question_id": null,
      "requires_media": false,
      "speaking_evidence": null
    },
    {
      "question_no": 13,
      "lesson_id": 3768633,
      "lesson_title": "Unit 1B: Animals - Lesson 1: That is a lion.",
      "skill_category": "vocabulary",
      "question_type": "Một lựa chọn",
      "question_text": "Listen and choose the correct answer. (Con hãy nghe và chọn câu đúng nhé.)",
      "correct_answer": "A. This is a tiger.",
      "difficulty": "easy",
      "reason": "Bài này đã học 39 ngày trước và học sinh đã trả lời sai câu này trước đó: điền/chọn \"C. That is a tiger.\" thay vì \"A. This is a tiger.\". Lỗi này khớp trực tiếp với chẩn đoán về việc em chưa ổn định cặp chỉ định từ this/that trong ngữ cảnh gần–xa.",
      "question_id": 372875,
      "requires_media": false,
      "speaking_evidence": null,
      "stem_media_urls": [],
      "comment_media_urls": [],
      "choice_previews": [
        {
          "letter": "A",
          "text": "A. This is a tiger.",
          "image_urls": [],
          "audio_urls": []
        },
        {
          "letter": "B",
          "text": "B. This is a lion.",
          "image_urls": [],
          "audio_urls": []
        },
        {
          "letter": "C",
          "text": "C. That is a tiger.",
          "image_urls": [],
          "audio_urls": []
        }
      ],
      "comment_plain": "Audio: This is a tiger. Dịch: Đây là con hổ. => Đáp án: A",
      "question_folder": "English Tutoring - Level 2"
    },
    {
      "question_no": 14,
      "lesson_id": 3690830,
      "lesson_title": "Unit 3A: Body parts - Lesson 3: I can swim.",
      "skill_category": "speaking",
      "question_type": "free_speaking",
      "question_text": "Answer in 1 full sentence: What can you do?",
      "correct_answer": null,
      "difficulty": "easy",
      "reason": "Bài này đã học 76 ngày trước và là một bài spaced review phù hợp để luyện nói có khung an toàn. Chẩn đoán cho thấy học sinh yếu ở free speaking/warmup, nhiều câu trả lời không liên quan hoặc đứt đoạn như “No.”, nên mẫu “I can ...” sẽ giúp em phản xạ đúng chủ đề hơn.",
      "question_id": null,
      "requires_media": false,
      "speaking_evidence": "No."
    },
    {
      "question_no": 15,
      "lesson_id": 3768630,
      "lesson_title": "Unit 4A: My face - Lesson 4: He has curly hair.",
      "skill_category": "speaking",
      "question_type": "free_speaking",
      "question_text": "Describe in 1 sentence: She has ...",
      "correct_answer": null,
      "difficulty": "medium",
      "reason": "Bài này đã học 48 ngày trước, cần nối từ vựng khuôn mặt với câu nói hoàn chỉnh vì chẩn đoán cho thấy học sinh có từ khóa nhưng chưa ghép được câu. Em từng nói các mẫu thiếu thành phần như “Lion big.”, nên bài nói theo khung “She has ...” sẽ giúp sửa lỗi câu cụt.",
      "question_id": null,
      "requires_media": false,
      "speaking_evidence": "Lion big."
    }
  ]
}